flet_gnav_bar/__init__.py
flet_gnav_bar/flet_gnav_bar.py
flutter/flet_gnav_bar/CHANGELOG.md
flutter/flet_gnav_bar/LICENSE
flutter/flet_gnav_bar/README.md
flutter/flet_gnav_bar/pubspec.yaml
flutter/flet_gnav_bar/lib/flet_gnav_bar.dart
flutter/flet_gnav_bar/lib/src/create_control.dart
flutter/flet_gnav_bar/lib/src/flet_gnav_bar.dart
flet_gnav_bar-0.0.2.dist-info/METADATA
flet_gnav_bar-0.0.2.dist-info/WHEEL
flet_gnav_bar-0.0.2.dist-info/top_level.txt
flet_gnav_bar-0.0.2.dist-info/RECORD
