Metadata-Version: 2.4
Name: flet_gnav_bar
Version: 0.0.2
Summary: A Google Navigation Bar control for Flet based on Aurélien Salomon's design.
Author-email: Soumalya Das <geniussantu1983@gmail.com>
Project-URL: Homepage, https://pro-grammer-sd.github.io/flet_gnav_bar/
Project-URL: Documentation, https://pro-grammer-sd.github.io/flet_gnav_bar/
Project-URL: Repository, https://github.com/pro-grammer-SD/flet_gnav_bar
Project-URL: Issues, https://github.com/pro-grammer-SD/flet_gnav_bar/issues
Requires-Python: >=3.9
Requires-Dist: flet>=0.28.3
